parallelmatx/__init__.py
parallelmatx/build.py
parallelmatx/normal.py
parallelmatx/parallel.py
parallelmatx/performance.py
parallematx-1.0.3.dist-info/LICENSE
parallematx-1.0.3.dist-info/METADATA
parallematx-1.0.3.dist-info/WHEEL
parallematx-1.0.3.dist-info/top_level.txt
parallematx-1.0.3.dist-info/RECORD
