Metadata-Version: 2.2
Name: parallematx
Version: 1.0.3
Summary: Parallel Matrix Multiplication with ProcessPoolExecutor
Home-page: https://github.com/Jackyzaz/ParallelMatX
Author: Jackyzaz
Author-email: soravit.sukkarn@gmail.com
License: MIT
Classifier: License :: OSI Approved :: MIT License
Classifier: Programming Language :: Python :: 3.10
Classifier: Operating System :: OS Independent
Requires-Python: >=3.10
License-File: LICENSE
Requires-Dist: bson>=0.5.10
Dynamic: author
Dynamic: author-email
Dynamic: classifier
Dynamic: description
Dynamic: description-content-type
Dynamic: home-page
Dynamic: license
Dynamic: requires-dist
Dynamic: requires-python
Dynamic: summary
